{
    "id": "18305363",
    "tms:id": "40110",
    "accession_number": "1924-34-14",
    "title": "Bow",
    "title_raw": null,
    "url": "http:\/\/collection.cooperhewitt.org\/objects\/18305363\/",
    "department_id": "35347501",
    "period_id": null,
    "media_id": "35371135",
    "type_id": "35283443",
    "date": null,
    "year_start": null,
    "year_end": null,
    "year_acquired": "1924",
    "decade": null,
    "woe:country_id": null,
    "medium": null,
    "markings": null,
    "signed": null,
    "inscribed": null,
    "provenance": null,
    "dimensions": null,
    "dimensions_raw": null,
    "creditline": null,
    "description": null,
    "justification": null,
    "videos": null,
    "woe:country": null,
    "type": "Bow",
    "images": [
        {
            "b": {
                "url": "http:\/\/images.collection.cooperhewitt.org\/69083_7a24dc40d9564271_b.jpg",
                "width": 702,
                "height": 1024,
                "is_primary": "1",
                "image_id": "69083"
            },
            "z": {
                "url": "http:\/\/images.collection.cooperhewitt.org\/69083_7a24dc40d9564271_z.jpg",
                "width": 439,
                "height": 640,
                "is_primary": "1",
                "image_id": "69083"
            },
            "n": {
                "url": "http:\/\/images.collection.cooperhewitt.org\/69083_7a24dc40d9564271_n.jpg",
                "width": 219,
                "height": 320,
                "is_primary": "1",
                "image_id": "69083"
            },
            "d": {
                "url": "http:\/\/images.collection.cooperhewitt.org\/69083_7a24dc40d9564271_d.gif",
                "width": 219,
                "height": 320,
                "is_primary": "1",
                "image_id": "69083"
            },
            "sq": {
                "url": "http:\/\/images.collection.cooperhewitt.org\/69083_7a24dc40d9564271_sq.jpg",
                "width": 300,
                "height": 300,
                "is_primary": "1",
                "image_id": "69083"
            }
        }
    ],
    "participants": [

    ],
    "tombstone": {
        "epitaph": "Bow. 1924-34-14."
    },
    "colors": [
        {
            "color": "#d7cbc9",
            "closest_crayola": "#cdc5c2",
            "closest_css3": "#d3d3d3",
            "closest_css4": "#d3d3d3"
        },
        {
            "color": "#372c2c",
            "closest_crayola": "#414a4c",
            "closest_css3": "#2f4f4f",
            "closest_css4": "#2f4f4f"
        },
        {
            "color": "#d0a5ab",
            "closest_crayola": "#ef98aa",
            "closest_css3": "#d2b48c",
            "closest_css4": "#d2b48c"
        },
        {
            "color": "#5e4548",
            "closest_crayola": "#414a4c",
            "closest_css3": "#556b2f",
            "closest_css4": "#556b2f"
        },
        {
            "color": "#6d5e59",
            "closest_crayola": "#6e5160",
            "closest_css3": "#696969",
            "closest_css4": "#696969"
        }
    ]
}