{
    "id": "18483709",
    "tms:id": "152717",
    "accession_number": "1974-52-234",
    "title": "Band",
    "title_raw": null,
    "url": "https:\/\/collection.cooperhewitt.org\/objects\/18483709\/",
    "department_id": "35347501",
    "period_id": null,
    "media_id": "112411",
    "type_id": "35254631",
    "date": null,
    "year_start": null,
    "year_end": null,
    "year_acquired": "1974",
    "decade": null,
    "woe:country_id": null,
    "medium": "Technique: bobbin lace (valencienne)",
    "markings": null,
    "signed": null,
    "inscribed": null,
    "provenance": null,
    "dimensions": null,
    "dimensions_raw": null,
    "creditline": null,
    "description": null,
    "justification": null,
    "gallery_text": null,
    "label_text": null,
    "videos": null,
    "on_display": null,
    "woe:country": null,
    "type": "Band",
    "images": [
        {
            "b": {
                "url": "https:\/\/images.collection.cooperhewitt.org\/138713_3f0125196233fb89_b.jpg",
                "width": 1024,
                "height": 185,
                "is_primary": "1",
                "image_id": "138713"
            },
            "z": {
                "url": "https:\/\/images.collection.cooperhewitt.org\/138713_3f0125196233fb89_z.jpg",
                "width": 640,
                "height": 116,
                "is_primary": "1",
                "image_id": "138713"
            },
            "n": {
                "url": "https:\/\/images.collection.cooperhewitt.org\/138713_3f0125196233fb89_n.jpg",
                "width": 320,
                "height": 58,
                "is_primary": "1",
                "image_id": "138713"
            },
            "d": {
                "url": "https:\/\/images.collection.cooperhewitt.org\/138713_3f0125196233fb89_d.gif",
                "width": 320,
                "height": 58,
                "is_primary": "1",
                "image_id": "138713"
            },
            "sq": {
                "url": "https:\/\/images.collection.cooperhewitt.org\/138713_3f0125196233fb89_sq.jpg",
                "width": 300,
                "height": 185,
                "is_primary": "1",
                "image_id": "138713"
            }
        }
    ],
    "participants": [

    ],
    "tombstone": {
        "epitaph": "Band. Technique: bobbin lace (valencienne). \n1974-52-234"
    },
    "colors": [

    ],
    "is_loan_object": 0
}