{
    "id": "18435331",
    "tms:id": "128085",
    "accession_number": "1960-83-53",
    "title": "Drawing (USA)",
    "title_raw": null,
    "url": "https:\/\/collection.cooperhewitt.org\/objects\/18435331\/",
    "department_id": "35347493",
    "period_id": null,
    "media_id": "35371135",
    "type_id": "35237093",
    "date": null,
    "year_start": null,
    "year_end": null,
    "year_acquired": "1960",
    "decade": null,
    "woe:country_id": "23424977",
    "medium": null,
    "markings": null,
    "signed": null,
    "inscribed": null,
    "provenance": null,
    "dimensions": null,
    "dimensions_raw": null,
    "creditline": null,
    "description": null,
    "justification": null,
    "gallery_text": null,
    "label_text": null,
    "videos": null,
    "on_display": null,
    "woe:country": "23424977",
    "type": "Drawing",
    "images": [
        {
            "b": {
                "url": "https:\/\/images.collection.cooperhewitt.org\/121579_b38ca47c213c8b40_b.jpg",
                "width": 831,
                "height": 1024,
                "is_primary": "1",
                "image_id": "121579"
            },
            "z": {
                "url": "https:\/\/images.collection.cooperhewitt.org\/121579_b38ca47c213c8b40_z.jpg",
                "width": 519,
                "height": 640,
                "is_primary": "1",
                "image_id": "121579"
            },
            "n": {
                "url": "https:\/\/images.collection.cooperhewitt.org\/121579_b38ca47c213c8b40_n.jpg",
                "width": 260,
                "height": 320,
                "is_primary": "1",
                "image_id": "121579"
            },
            "d": {
                "url": "https:\/\/images.collection.cooperhewitt.org\/121579_b38ca47c213c8b40_d.gif",
                "width": 260,
                "height": 320,
                "is_primary": "1",
                "image_id": "121579"
            },
            "sq": {
                "url": "https:\/\/images.collection.cooperhewitt.org\/121579_b38ca47c213c8b40_sq.jpg",
                "width": 300,
                "height": 300,
                "is_primary": "1",
                "image_id": "121579"
            }
        },
        {
            "b": {
                "url": "https:\/\/images.collection.cooperhewitt.org\/216370_486445c1cb0fd375_b.jpg",
                "width": 1024,
                "height": 718,
                "is_primary": "0",
                "image_id": "216370"
            },
            "z": {
                "url": "https:\/\/images.collection.cooperhewitt.org\/216370_486445c1cb0fd375_z.jpg",
                "width": 640,
                "height": 448,
                "is_primary": "0",
                "image_id": "216370"
            },
            "n": {
                "url": "https:\/\/images.collection.cooperhewitt.org\/216370_486445c1cb0fd375_n.jpg",
                "width": 320,
                "height": 224,
                "is_primary": "0",
                "image_id": "216370"
            },
            "d": {
                "url": "https:\/\/images.collection.cooperhewitt.org\/216370_486445c1cb0fd375_d.gif",
                "width": 320,
                "height": 224,
                "is_primary": "0",
                "image_id": "216370"
            },
            "sq": {
                "url": "https:\/\/images.collection.cooperhewitt.org\/216370_486445c1cb0fd375_sq.jpg",
                "width": 300,
                "height": 300,
                "is_primary": "0",
                "image_id": "216370"
            }
        }
    ],
    "participants": [
        {
            "person_id": "18536881",
            "role_id": "35351535",
            "person_name": "Allyn Cox",
            "person_date": "",
            "role_name": "Donor",
            "role_display_name": "Donated by",
            "person_url": "https:\/\/collection.cooperhewitt.org\/people\/18536881\/",
            "role_url": "https:\/\/collection.cooperhewitt.org\/roles\/35351535\/"
        }
    ],
    "tombstone": {
        "epitaph": "Drawing (USA). 1960-83-53."
    },
    "colors": [
        {
            "color": "#716952",
            "closest_crayola": "#85754e",
            "closest_css3": "#696969",
            "closest_css4": "#696969"
        },
        {
            "color": "#cdc7ae",
            "closest_crayola": "#cdc5c2",
            "closest_css3": "#c0c0c0",
            "closest_css4": "#c0c0c0"
        },
        {
            "color": "#90856c",
            "closest_crayola": "#9f8170",
            "closest_css3": "#808080",
            "closest_css4": "#808080"
        }
    ],
    "woe:country_name": "United States",
    "is_loan_object": 0
}