{
  "display_date": "1775", 
  "credit_line": "Museum purchase through gift of various donors and from Eleanor G. Hewitt Fund", 
  "date_end": "1775", 
  "period": "", 
  "dynasty": "", 
  "culture": "Italian", 
  "id": "61219", 
  "style": "", 
  "date_begin": "1775", 
  "dimensions": "33.5 x 25.9 cm (13 3/16 x 10 3/16 in.)\r\nMat:  45.7 x 35.6 cm (18 x 14 in.)", 
  "copyright": "", 
  "title": "Wall Fountain", 
  "provenance": "Giovanni Piancastelli; Mr. and Mrs. Edward D. Brandegee", 
  "credit_line_repro": "", 
  "invno": "1938-88-1013                              ", 
  "movement": "", 
  "medium": "Graphite, gray wash\r\nSupport: laid paper", 
  "media_id": "", 
  "description": "", 
  "classification_id": "12", 
  "restrictions": "", 
  "school": "", 
  "name": "Drawing", 
  "region": "", 
  "caption": "", 
  "department_id": "2"
}