{
    "id": "18646853",
    "tms:id": "198331",
    "accession_number": "1993-76-7",
    "title": "Pin, 1993-76-7",
    "url": "http:\/\/collection.cooperhewitt.org\/objects\/18646853\/",
    "department_id": "35347497",
    "period_id": null,
    "date": null,
    "year_start": null,
    "year_end": null,
    "year_acquired": "1993",
    "decade": null,
    "woe:country": "23424977",
    "medium": "Resin, copper, mother-of-pearl, metal foil",
    "markings": null,
    "signed": null,
    "inscribed": null,
    "provenance": null,
    "dimensions": "Overall: 6 x 7 x 0.9 cm (2 3\/8 x 2 3\/4 x 3\/8 in.)",
    "creditline": "Gift of Armand G. Winfield",
    "description": null,
    "justification": null,
    "culture": null,
    "style": null,
    "type": {
        "id": "35249363",
        "name": "pin"
    },
    "images": [
        {
            "b": {
                "url": "http:\/\/images.collection.cooperhewitt.org.s3.amazonaws.com\/25854_3302271797b0f1e8_b.jpg",
                "width": 999,
                "height": 1024,
                "is_primary": "1"
            },
            "n": {
                "url": "http:\/\/images.collection.cooperhewitt.org.s3.amazonaws.com\/25854_3302271797b0f1e8_n.jpg",
                "width": 312,
                "height": 320,
                "is_primary": "1"
            },
            "z": {
                "url": "http:\/\/images.collection.cooperhewitt.org.s3.amazonaws.com\/25854_3302271797b0f1e8_z.jpg",
                "width": 624,
                "height": 640,
                "is_primary": "1"
            }
        },
        {
            "b": {
                "url": "http:\/\/images.collection.cooperhewitt.org.s3.amazonaws.com\/25855_4190f67febb5dbf0_b.jpg",
                "width": 1024,
                "height": 898,
                "is_primary": "0"
            },
            "n": {
                "url": "http:\/\/images.collection.cooperhewitt.org.s3.amazonaws.com\/25855_4190f67febb5dbf0_n.jpg",
                "width": 320,
                "height": 281,
                "is_primary": "0"
            },
            "z": {
                "url": "http:\/\/images.collection.cooperhewitt.org.s3.amazonaws.com\/25855_4190f67febb5dbf0_z.jpg",
                "width": 640,
                "height": 561,
                "is_primary": "0"
            }
        }
    ],
    "participants": [
        {
            "person_id": "18044813",
            "role_id": "35236655",
            "person_name": "Ericka Gorecka-Ekan",
            "role_name": "Designer",
            "person_url": "http:\/\/collection.cooperhewitt.org\/people\/18044813\/",
            "role_url": "http:\/\/collection.cooperhewitt.org\/roles\/35236655\/"
        }
    ],
    "exhibitions": [

    ]
}