{
    "id": "18630349",
    "tms:id": "190015",
    "accession_number": "1988-62-323",
    "title": "Drawing",
    "title_raw": null,
    "url": "https:\/\/collection.cooperhewitt.org\/objects\/18630349\/",
    "department_id": "35347493",
    "period_id": null,
    "media_id": "35371135",
    "type_id": "35237093",
    "date": null,
    "year_start": null,
    "year_end": null,
    "year_acquired": "1988",
    "decade": null,
    "woe:country_id": null,
    "medium": null,
    "markings": null,
    "signed": null,
    "inscribed": null,
    "provenance": null,
    "dimensions": null,
    "dimensions_raw": null,
    "creditline": "Museum purchase from Smithsonian Collections Acquisition and Decorative Arts Association Acquisition Funds",
    "description": null,
    "justification": null,
    "gallery_text": null,
    "label_text": null,
    "videos": null,
    "on_display": null,
    "woe:country": null,
    "type": "Drawing",
    "images": [
        {
            "b": {
                "url": "https:\/\/images.collection.cooperhewitt.org\/140471_1a09a637b5dc84e1_b.jpg",
                "width": 1024,
                "height": 361,
                "is_primary": "1",
                "image_id": "140471"
            },
            "z": {
                "url": "https:\/\/images.collection.cooperhewitt.org\/140471_1a09a637b5dc84e1_z.jpg",
                "width": 640,
                "height": 226,
                "is_primary": "1",
                "image_id": "140471"
            },
            "n": {
                "url": "https:\/\/images.collection.cooperhewitt.org\/140471_1a09a637b5dc84e1_n.jpg",
                "width": 320,
                "height": 113,
                "is_primary": "1",
                "image_id": "140471"
            },
            "d": {
                "url": "https:\/\/images.collection.cooperhewitt.org\/140471_1a09a637b5dc84e1_d.gif",
                "width": 320,
                "height": 113,
                "is_primary": "1",
                "image_id": "140471"
            },
            "sq": {
                "url": "https:\/\/images.collection.cooperhewitt.org\/140471_1a09a637b5dc84e1_sq.jpg",
                "width": 300,
                "height": 300,
                "is_primary": "1",
                "image_id": "140471"
            }
        }
    ],
    "participants": [
        {
            "person_id": "18538455",
            "role_id": "35352249",
            "person_name": "Wolfgang Ruf",
            "person_date": "",
            "role_name": "Vendor",
            "role_display_name": "Purchased from",
            "person_url": "https:\/\/collection.cooperhewitt.org\/people\/18538455\/",
            "role_url": "https:\/\/collection.cooperhewitt.org\/roles\/35352249\/"
        }
    ],
    "tombstone": {
        "epitaph": "Drawing. Museum purchase from Smithsonian Collections Acquisition and Decorative Arts Association Acquisition Funds. 1988-62-323."
    },
    "colors": [
        {
            "color": "#efe6c7",
            "closest_crayola": "#efdecd",
            "closest_css3": "#ffe4c4",
            "closest_css4": "#ffe4c4"
        },
        {
            "color": "#3e548e",
            "closest_crayola": "#2e5894",
            "closest_css3": "#483d8b",
            "closest_css4": "#483d8b"
        },
        {
            "color": "#7e537e",
            "closest_crayola": "#8d4e85",
            "closest_css3": "#696969",
            "closest_css4": "#696969"
        },
        {
            "color": "#667182",
            "closest_crayola": "#757575",
            "closest_css3": "#708090",
            "closest_css4": "#708090"
        },
        {
            "color": "#6b5554",
            "closest_crayola": "#6e5160",
            "closest_css3": "#696969",
            "closest_css4": "#696969"
        }
    ],
    "is_loan_object": 0
}