{
  "display_date": "19th century", 
  "credit_line": "Gift of Clarence Hoblitzelle", 
  "date_end": "1900", 
  "period": "", 
  "dynasty": "", 
  "culture": "", 
  "id": "18781", 
  "style": "", 
  "date_begin": "1801", 
  "dimensions": "Warp x Weft: 73.5 x 144.7 cm (28 15/16 x 56 15/16 in.)", 
  "copyright": "", 
  "title": "Fragment", 
  "provenance": "", 
  "credit_line_repro": "", 
  "invno": "1912-10-8-a/c", 
  "thumbnail": "http://data.cooperhewitt.org/media/350/42297.JPG", 
  "movement": "", 
  "medium": "Medium: silk\r\nTechnique: 5-harness satin damask", 
  "media_id": "42297", 
  "description": "White damask with a pattern of symmetrically swinging broad bands with flowers and foliage enclosing central symmetrical group of flowers, grapes and wheat.", 
  "classification_id": "259", 
  "restrictions": "", 
  "school": "", 
  "name": "Fragment", 
  "region": "", 
  "caption": "", 
  "department_id": "5"
}