{
    "id": "18606853",
    "tms:id": "96952",
    "accession_number": "1947-72-4",
    "title": "Sidewall (England), 1946",
    "title_raw": null,
    "url": "https:\/\/collection.cooperhewitt.org\/objects\/18606853\/",
    "department_id": "35347503",
    "period_id": null,
    "media_id": "35414653",
    "type_id": "35256475",
    "date": "1946",
    "year_start": 1946,
    "year_end": 1946,
    "year_acquired": "1947",
    "decade": "1940",
    "woe:country_id": "23424975",
    "medium": "Machine-printed",
    "markings": null,
    "signed": null,
    "inscribed": null,
    "provenance": null,
    "dimensions": "62 x 55.5 cm (24 7\/16 x 21 7\/8 in.)",
    "dimensions_raw": {
        "height": [
            "62.00",
            "centimeters"
        ],
        "width": [
            "55.50",
            "centimeters"
        ]
    },
    "creditline": "Gift of Rose J. Dirksen",
    "description": "Formalized romantic pastoral and floral motifs. The more important of these shows a French shepherdess kneeling beside her sheep and dropping morsels of food in the mouth of a young dog. Behind her is a \"liberty pole\".",
    "justification": null,
    "gallery_text": null,
    "label_text": null,
    "videos": null,
    "on_display": null,
    "woe:country": "23424975",
    "type": "Sidewall",
    "images": [
        {
            "b": {
                "url": "https:\/\/images.collection.cooperhewitt.org\/20160_3550c47332be0981_b.jpg",
                "width": 906,
                "height": 1024,
                "is_primary": "1",
                "image_id": "20160"
            },
            "z": {
                "url": "https:\/\/images.collection.cooperhewitt.org\/20160_3550c47332be0981_z.jpg",
                "width": 566,
                "height": 640,
                "is_primary": "1",
                "image_id": "20160"
            },
            "n": {
                "url": "https:\/\/images.collection.cooperhewitt.org\/20160_3550c47332be0981_n.jpg",
                "width": 283,
                "height": 320,
                "is_primary": "1",
                "image_id": "20160"
            },
            "d": {
                "url": "https:\/\/images.collection.cooperhewitt.org\/20160_3550c47332be0981_d.gif",
                "width": 283,
                "height": 320,
                "is_primary": "1",
                "image_id": "20160"
            },
            "sq": {
                "url": "https:\/\/images.collection.cooperhewitt.org\/20160_3550c47332be0981_sq.jpg",
                "width": 300,
                "height": 300,
                "is_primary": "1",
                "image_id": "20160"
            }
        }
    ],
    "participants": [
        {
            "person_id": "18047829",
            "role_id": "35352245",
            "person_name": "Horace L. Hotchkiss, Jr.",
            "person_date": "",
            "role_name": "Cataloguer",
            "role_display_name": "Catalogued by",
            "person_url": "https:\/\/collection.cooperhewitt.org\/people\/18047829\/",
            "role_url": "https:\/\/collection.cooperhewitt.org\/roles\/35352245\/"
        },
        {
            "person_id": "68736361",
            "role_id": "35351535",
            "person_name": "Rose J. Dirksen",
            "person_date": "",
            "role_name": "Donor",
            "role_display_name": "Donated by",
            "person_url": "https:\/\/collection.cooperhewitt.org\/people\/68736361\/",
            "role_url": "https:\/\/collection.cooperhewitt.org\/roles\/35351535\/"
        }
    ],
    "tombstone": {
        "epitaph": "Sidewall (England), 1946. Machine-printed. \nGift of Rose J. Dirksen. 1947-72-4"
    },
    "colors": [
        {
            "color": "#888d83",
            "closest_crayola": "#95918c",
            "closest_css3": "#808080",
            "closest_css4": "#808080"
        },
        {
            "color": "#716b4c",
            "closest_crayola": "#85754e",
            "closest_css3": "#696969",
            "closest_css4": "#696969"
        },
        {
            "color": "#978874",
            "closest_crayola": "#9f8170",
            "closest_css3": "#808080",
            "closest_css4": "#808080"
        },
        {
            "color": "#3d6d5c",
            "closest_crayola": "#4a646c",
            "closest_css3": "#2e8b57",
            "closest_css4": "#2e8b57"
        },
        {
            "color": "#474331",
            "closest_crayola": "#414a4c",
            "closest_css3": "#2f4f4f",
            "closest_css4": "#2f4f4f"
        }
    ],
    "woe:country_name": "United Kingdom",
    "is_loan_object": 0
}