{
    "id":"18141641",
    "tms:id":"13358",
    "accession_number":"1904-20-187",
    "title":"Mount, 1904-20-187",
    "url":"http:\/\/collection.cooperhewitt.org\/objects\/18141641\/",
    "department_id":"35347497",
    "period_id":null,
    "date":null,
    "year_start":null,
    "year_end":null,
    "year_acquired":"1904",
    "decade":null,
    "woe:country":null,
    "medium":null,
    "markings":null,
    "signed":null,
    "inscribed":null,
    "provenance":null,
    "dimensions":"L x W x D: 9.6 cm (3 3\/4 in.)",
    "creditline":"Gift of Jacob H. Schiff",
    "description":null,
    "justification":null,
    "culture":null,
    "style":null,
    "type":{
        "id":"35259245",
        "name":"Mount"
    },
    "images":[

    ],
    "participants":[

    ],
    "exhibitions":[

    ]
}