{
    "id": "18469765",
    "tms:id": "145520",
    "accession_number": "1969-35-14-h",
    "title": "Drawing (USA)",
    "title_raw": null,
    "url": "https:\/\/collection.cooperhewitt.org\/objects\/18469765\/",
    "has_no_known_copyright": null,
    "department_id": "35347493",
    "period_id": null,
    "media_id": "35371135",
    "type_id": "35237093",
    "date": null,
    "year_start": null,
    "year_end": null,
    "year_acquired": "1969",
    "decade": null,
    "woe:country_id": "23424977",
    "medium": null,
    "markings": null,
    "signed": null,
    "inscribed": null,
    "provenance": null,
    "dimensions": null,
    "dimensions_raw": null,
    "creditline": null,
    "description": null,
    "justification": null,
    "gallery_text": null,
    "label_text": null,
    "videos": null,
    "on_display": null,
    "woe:country": "23424977",
    "type": "Drawing",
    "images": [
        {
            "b": {
                "url": "https:\/\/images.collection.cooperhewitt.org\/178876_a2d89aa2cf37cb97_b.jpg",
                "width": 737,
                "height": 1024,
                "is_primary": "1",
                "image_id": "178876"
            },
            "z": {
                "url": "https:\/\/images.collection.cooperhewitt.org\/178876_a2d89aa2cf37cb97_z.jpg",
                "width": 461,
                "height": 640,
                "is_primary": "1",
                "image_id": "178876"
            },
            "n": {
                "url": "https:\/\/images.collection.cooperhewitt.org\/178876_a2d89aa2cf37cb97_n.jpg",
                "width": 230,
                "height": 320,
                "is_primary": "1",
                "image_id": "178876"
            },
            "d": {
                "url": "https:\/\/images.collection.cooperhewitt.org\/178876_a2d89aa2cf37cb97_d.gif",
                "width": 230,
                "height": 320,
                "is_primary": "1",
                "image_id": "178876"
            },
            "sq": {
                "url": "https:\/\/images.collection.cooperhewitt.org\/178876_a2d89aa2cf37cb97_sq.jpg",
                "width": 300,
                "height": 300,
                "is_primary": "1",
                "image_id": "178876"
            }
        }
    ],
    "participants": [

    ],
    "tombstone": {
        "epitaph": "Drawing (USA); 1969-35-14-h"
    },
    "colors": [
        {
            "color": "#aeab88",
            "closest_crayola": "#bab86c",
            "closest_css3": "#bc8f8f",
            "closest_css4": "#bc8f8f"
        },
        {
            "color": "#8a8575",
            "closest_crayola": "#9f8170",
            "closest_css3": "#808080",
            "closest_css4": "#808080"
        },
        {
            "color": "#6a6a5b",
            "closest_crayola": "#6e5160",
            "closest_css3": "#696969",
            "closest_css4": "#696969"
        }
    ],
    "woe:country_name": "United States",
    "is_loan_object": 0
}