{
  "display_date": "ca. 1795", 
  "credit_line": "Bequest of Elinor Merrell", 
  "date_end": "1805", 
  "period": "", 
  "dynasty": "", 
  "culture": "", 
  "id": "209126", 
  "style": "", 
  "date_begin": "1785", 
  "dimensions": "Warp: 170cm (66 1/2in.). Weft (3 pieces sewn together)\r\n126cm (49 in.).", 
  "copyright": "", 
  "title": "Paul et Virginie", 
  "provenance": "", 
  "credit_line_repro": "", 
  "invno": "1995-50-141                               ", 
  "movement": "Research in progress", 
  "medium": "Medium: cotton\r\nTechnique: printed by engraved plate on plain weave", 
  "media_id": "15152", 
  "description": "A series of pictorial vignettes illustrating the story of Paul and Virginia as originally told in the novel by Bernadin de St-Pierre(1788) and later in an opera (which changed the ending of the original story) by Kreutzer and Favieres (1791). Scenes include a shipwreck and scenes on a tropical island. In red on white.", 
  "classification_id": "266", 
  "restrictions": "", 
  "school": "", 
  "name": "Textile", 
  "region": "", 
  "caption": "", 
  "department_id": "5"
}