{
    "id": "18639547",
    "tms:id": "194637",
    "accession_number": "1992-167-4",
    "title": "Print, Invitation to The First Graduation of Communist Specialists in Polygraphy and Publishing, July 24, 1931, 1931",
    "title_raw": "Invitation to The First Graduation of Communist Specialists in Polygraphy and Publishing, July 24, 1931",
    "url": "http:\/\/collection.cooperhewitt.org\/objects\/18639547\/",
    "department_id": "35347493",
    "period_id": null,
    "media_id": "35519975",
    "type_id": "35236873",
    "date": "1931",
    "year_start": 1931,
    "year_end": 1931,
    "year_acquired": "1992",
    "decade": "1930",
    "woe:country_id": "23424936",
    "medium": "Lithograph, typography on paper",
    "markings": null,
    "signed": null,
    "inscribed": "Imprinted in brown ink, lower left, publication information",
    "provenance": "Rosa Esman Gallery, New York",
    "dimensions": "9.4 x 14 cm (3 11\/16 x 5 1\/2 in.)\n(unfolded): 9.4 x 27.3 cm (3 11\/16 x 10 3\/4 in.)",
    "dimensions_raw": {
        "height": [
            "9.40",
            "centimeters"
        ],
        "width": [
            "27.30",
            "centimeters"
        ]
    },
    "creditline": "Museum purchase through gift of Lucy Work Hewitt",
    "description": "Invitation in brown and orange ink. Left side has brown text on orange ground; right side has brown and orange text  on white ground.",
    "justification": null,
    "gallery_text": null,
    "label_text": null,
    "videos": null,
    "on_display": null,
    "woe:country": "23424936",
    "type": "Print",
    "images": [
        {
            "b": {
                "url": "https:\/\/images.collection.cooperhewitt.org\/51460_28a60ac6eb55a212_b.jpg",
                "width": 1024,
                "height": 382,
                "is_primary": "1",
                "image_id": "51460"
            },
            "z": {
                "url": "https:\/\/images.collection.cooperhewitt.org\/51460_28a60ac6eb55a212_z.jpg",
                "width": 640,
                "height": 238,
                "is_primary": "1",
                "image_id": "51460"
            },
            "n": {
                "url": "https:\/\/images.collection.cooperhewitt.org\/51460_28a60ac6eb55a212_n.jpg",
                "width": 320,
                "height": 119,
                "is_primary": "1",
                "image_id": "51460"
            },
            "d": {
                "url": "https:\/\/images.collection.cooperhewitt.org\/51460_28a60ac6eb55a212_d.gif",
                "width": 320,
                "height": 119,
                "is_primary": "1",
                "image_id": "51460"
            },
            "sq": {
                "url": "https:\/\/images.collection.cooperhewitt.org\/51460_28a60ac6eb55a212_sq.jpg",
                "width": 300,
                "height": 300,
                "is_primary": "1",
                "image_id": "51460"
            }
        }
    ],
    "participants": [
        {
            "person_id": "51676457",
            "role_id": "35352245",
            "person_name": "Karin Zonis",
            "person_date": "",
            "role_name": "Cataloguer",
            "role_display_name": "Catalogued by",
            "person_url": "http:\/\/collection.cooperhewitt.org\/people\/51676457\/",
            "role_url": "http:\/\/collection.cooperhewitt.org\/roles\/35352245\/"
        },
        {
            "person_id": "18047461",
            "role_id": "35352245",
            "person_name": "Marilyn Symmes",
            "person_date": "",
            "role_name": "Cataloguer",
            "role_display_name": "Catalogued by",
            "person_url": "http:\/\/collection.cooperhewitt.org\/people\/18047461\/",
            "role_url": "http:\/\/collection.cooperhewitt.org\/roles\/35352245\/"
        },
        {
            "person_id": "18048035",
            "role_id": "35352245",
            "person_name": "Hedy Backlin-Landman",
            "person_date": "",
            "role_name": "Cataloguer",
            "role_display_name": "Catalogued by",
            "person_url": "http:\/\/collection.cooperhewitt.org\/people\/18048035\/",
            "role_url": "http:\/\/collection.cooperhewitt.org\/roles\/35352245\/"
        },
        {
            "person_id": "18041207",
            "role_id": "35352249",
            "person_name": "ROSA ESMAN GALLERY",
            "person_date": "",
            "role_name": "Vendor",
            "role_display_name": "Purchased from",
            "person_url": "http:\/\/collection.cooperhewitt.org\/people\/18041207\/",
            "role_url": "http:\/\/collection.cooperhewitt.org\/roles\/35352249\/"
        }
    ],
    "tombstone": {
        "epitaph": "Print, Invitation to The First Graduation of Communist Specialists in Polygraphy and Publishing, July 24, 1931, 1931. Lithograph, typography on paper. \nMuseum purchase through gift of Lucy Work Hewitt. 1992-167-4."
    },
    "colors": [
        {
            "color": "#d06529",
            "closest_crayola": "#c46210",
            "closest_css3": "#d2691e",
            "closest_css4": "#d2691e"
        },
        {
            "color": "#e3d5b9",
            "closest_crayola": "#efcdb8",
            "closest_css3": "#f5deb3",
            "closest_css4": "#f5deb3"
        },
        {
            "color": "#563b2f",
            "closest_crayola": "#714b23",
            "closest_css3": "#556b2f",
            "closest_css4": "#556b2f"
        },
        {
            "color": "#c4a181",
            "closest_crayola": "#cd9575",
            "closest_css3": "#bc8f8f",
            "closest_css4": "#bc8f8f"
        },
        {
            "color": "#924520",
            "closest_crayola": "#714b23",
            "closest_css3": "#8b4513",
            "closest_css4": "#8b4513"
        }
    ],
    "woe:country_name": "Russia"
}