{
    "id": "18452119",
    "tms:id": "136587",
    "accession_number": "1964-5-13",
    "title": "Print, Proposed Convocation Tower, Madison Square (Northeast Corner of Madison Avenue and East 26th Streeet), 1921",
    "title_raw": "Proposed Convocation Tower, Madison Square (Northeast Corner of Madison Avenue and East 26th Streeet)",
    "url": "https:\/\/collection.cooperhewitt.org\/objects\/18452119\/",
    "has_no_known_copyright": "1",
    "department_id": "35347493",
    "period_id": "35417049",
    "media_id": "35421313",
    "type_id": "35236873",
    "date": "1921",
    "year_start": 1921,
    "year_end": 1921,
    "year_acquired": "1964",
    "decade": "1920",
    "woe:country_id": "23424977",
    "medium": "photostat mounted on illustration board",
    "markings": null,
    "signed": "In graphite lower right Hugh Ferris - Del.",
    "inscribed": "Verso: In graphite upper right by the artist: Hugh Ferriss \/ 101 Park Av \/ (Vanderbilt - 3680); in black crayon upper center: Hugh Ferriss \/ 210 W. 57 (crossed out in graphite0; in black crayon at center: B.G. Goodhue \/ 2 W. 47 BO (?) (crossed out in graphite); in graphite in another hand right center: 5ft Hugh \/ see me",
    "provenance": "Mrs. Hugh Ferriss; 1964: acquired by Museum",
    "dimensions": "63.8 x 37.1cm (25 1\/8 x 14 5\/8in.)\nMat: 71.1 \u00d7 55.9 cm (28 \u00d7 22 in.)",
    "dimensions_raw": {
        "height": [
            "63.80",
            "centimeters"
        ],
        "width": [
            "37.10",
            "centimeters"
        ]
    },
    "creditline": "Gift of Mrs. Hugh Ferriss",
    "description": "Night scene of a skyscraper consisting of a massed cluster of low tiered sections below culminating in a monumental tower. The structure is illuminated by the city street lights below and streams of light from a chapel- like central section. A white cross is visible at the top of the tower. Pedestrians walk among silhouetted leafless trees below.",
    "justification": null,
    "gallery_text": null,
    "label_text": null,
    "videos": null,
    "on_display": "1",
    "woe:country": "23424977",
    "type": "Print",
    "images": [
        {
            "x": {
                "url": "https:\/\/images.collection.cooperhewitt.org\/59572_b467c4b9695a2f10_x.jpg",
                "width": 1727,
                "height": 3000,
                "is_primary": "1",
                "image_id": "59572"
            },
            "b": {
                "url": "https:\/\/images.collection.cooperhewitt.org\/59572_e7f690a390f6f85b_b.jpg",
                "width": 590,
                "height": 1024,
                "is_primary": "1",
                "image_id": "59572"
            },
            "z": {
                "url": "https:\/\/images.collection.cooperhewitt.org\/59572_e7f690a390f6f85b_z.jpg",
                "width": 368,
                "height": 640,
                "is_primary": "1",
                "image_id": "59572"
            },
            "n": {
                "url": "https:\/\/images.collection.cooperhewitt.org\/59572_e7f690a390f6f85b_n.jpg",
                "width": 184,
                "height": 320,
                "is_primary": "1",
                "image_id": "59572"
            },
            "d": {
                "url": "https:\/\/images.collection.cooperhewitt.org\/59572_e7f690a390f6f85b_d.gif",
                "width": 184,
                "height": 320,
                "is_primary": "1",
                "image_id": "59572"
            },
            "sq": {
                "url": "https:\/\/images.collection.cooperhewitt.org\/59572_e7f690a390f6f85b_sq.jpg",
                "width": 300,
                "height": 300,
                "is_primary": "1",
                "image_id": "59572"
            }
        },
        {
            "x": {
                "url": "https:\/\/images.collection.cooperhewitt.org\/205673_ae619e5cb5a3f0ff_x.jpg",
                "width": 2437,
                "height": 4096,
                "is_primary": "0",
                "image_id": "205673"
            },
            "b": {
                "url": "https:\/\/images.collection.cooperhewitt.org\/205673_cfa23c8ae0851716_b.jpg",
                "width": 610,
                "height": 1024,
                "is_primary": "0",
                "image_id": "205673"
            },
            "z": {
                "url": "https:\/\/images.collection.cooperhewitt.org\/205673_cfa23c8ae0851716_z.jpg",
                "width": 381,
                "height": 640,
                "is_primary": "0",
                "image_id": "205673"
            },
            "n": {
                "url": "https:\/\/images.collection.cooperhewitt.org\/205673_cfa23c8ae0851716_n.jpg",
                "width": 191,
                "height": 320,
                "is_primary": "0",
                "image_id": "205673"
            },
            "d": {
                "url": "https:\/\/images.collection.cooperhewitt.org\/205673_cfa23c8ae0851716_d.gif",
                "width": 191,
                "height": 320,
                "is_primary": "0",
                "image_id": "205673"
            },
            "sq": {
                "url": "https:\/\/images.collection.cooperhewitt.org\/205673_cfa23c8ae0851716_sq.jpg",
                "width": 300,
                "height": 300,
                "is_primary": "0",
                "image_id": "205673"
            }
        }
    ],
    "participants": [
        {
            "person_id": "18056393",
            "role_id": "35351535",
            "person_name": "Mrs. Hugh Ferriss",
            "person_date": "",
            "role_name": "Donor",
            "role_display_name": "Donated by",
            "person_url": "https:\/\/collection.cooperhewitt.org\/people\/18056393\/",
            "role_url": "https:\/\/collection.cooperhewitt.org\/roles\/35351535\/"
        },
        {
            "person_id": "18042513",
            "role_id": "35236695",
            "person_name": "Hugh Ferriss",
            "person_date": "American, 1889\u20131962",
            "role_name": "Delineator",
            "role_display_name": "Delineator:",
            "person_url": "https:\/\/collection.cooperhewitt.org\/people\/18042513\/",
            "role_url": "https:\/\/collection.cooperhewitt.org\/roles\/35236695\/"
        }
    ],
    "tombstone": {
        "epitaph": "Print, Proposed Convocation Tower, Madison Square (Northeast Corner of Madison Avenue and East 26th Streeet), 1921; Delineator: Hugh Ferriss (American, 1889\u20131962); USA; photostat mounted on illustration board; 63.8 x 37.1cm (25 1\/8 x 14 5\/8in.)\nMat: 71.1 \u00d7 55.9 cm (28 \u00d7 22 in.); Gift of Mrs. Hugh Ferriss; 1964-5-13"
    },
    "colors": [
        {
            "color": "#555042",
            "closest_crayola": "#414a4c",
            "closest_css3": "#556b2f",
            "closest_css4": "#556b2f"
        },
        {
            "color": "#766f59",
            "closest_crayola": "#85754e",
            "closest_css3": "#696969",
            "closest_css4": "#696969"
        },
        {
            "color": "#978b6c",
            "closest_crayola": "#9f8170",
            "closest_css3": "#808080",
            "closest_css4": "#808080"
        },
        {
            "color": "#bcb092",
            "closest_crayola": "#deaa88",
            "closest_css3": "#d2b48c",
            "closest_css4": "#d2b48c"
        }
    ],
    "woe:country_name": "United States",
    "is_loan_object": 0
}