{
    "id": "18113627",
    "tms:id": "8659",
    "accession_number": "1901-39-2078",
    "title": "Drawing, \"Godfrey de Bouillon, after Giulio Romano and Raphael Sanzio\", ca. 1820",
    "url": "http:\/\/collection.cooperhewitt.org\/objects\/18113627\/",
    "department_id": "35347493",
    "period_id": "35417089",
    "date": "ca. 1820",
    "year_start": null,
    "year_end": null,
    "year_acquired": "1901",
    "decade": null,
    "woe:country": "23424853",
    "medium": "Pen and ink, brush and sepia wash over traces of graphite on laid paper",
    "markings": "Watermark: bottom part of lily in double oval",
    "signed": null,
    "inscribed": "Inscribed in ink, inside the bracket over Godfrey: VENVI\/ XCVI",
    "provenance": null,
    "dimensions": "21.3 x 20.6 cm (8 3\/8 x 8 1\/8 in.)",
    "creditline": "Museum purchase through gift of various donors",
    "description": null,
    "justification": null,
    "culture": "Italian",
    "style": null,
    "type": {
        "id": "35237093",
        "name": "Drawing"
    },
    "images": [

    ],
    "participants": [
        {
            "person_id": "18042405",
            "role_id": "35236655",
            "person_name": "Felice Giani",
            "role_name": "Designer",
            "person_url": "http:\/\/collection.cooperhewitt.org\/people\/18042405\/",
            "role_url": "http:\/\/collection.cooperhewitt.org\/roles\/35236655\/"
        }
    ],
    "exhibitions": [

    ]
}